ApacheCordovaKaifaZhinan/README.md
ApacheCordovaKaifaZhinan/__init__.py
ApacheCordovaKaifaZhinan/__main__.py
ApacheCordovaKaifaZhinan/file.epub
ApacheCordovaKaifaZhinan/index.html
ApacheCordovaKaifaZhinan/css/__init__.py
ApacheCordovaKaifaZhinan/css/annotations.css
ApacheCordovaKaifaZhinan/css/main.css
ApacheCordovaKaifaZhinan/css/normalize.css
ApacheCordovaKaifaZhinan/css/popup.css
ApacheCordovaKaifaZhinan/font/__init__.py
ApacheCordovaKaifaZhinan/font/fontello.eot
ApacheCordovaKaifaZhinan/font/fontello.svg
ApacheCordovaKaifaZhinan/font/fontello.ttf
ApacheCordovaKaifaZhinan/font/fontello.woff
ApacheCordovaKaifaZhinan/img/__init__.py
ApacheCordovaKaifaZhinan/img/annotator-glyph-sprite.png
ApacheCordovaKaifaZhinan/img/annotator-icon-sprite.png
ApacheCordovaKaifaZhinan/img/apple-touch-icon.png
ApacheCordovaKaifaZhinan/img/cancelfullscreen.png
ApacheCordovaKaifaZhinan/img/close.png
ApacheCordovaKaifaZhinan/img/fullscreen.png
ApacheCordovaKaifaZhinan/img/loader.gif
ApacheCordovaKaifaZhinan/img/menu-icon.png
ApacheCordovaKaifaZhinan/img/save.png
ApacheCordovaKaifaZhinan/img/saved.png
ApacheCordovaKaifaZhinan/img/settings-s.png
ApacheCordovaKaifaZhinan/img/settings.png
ApacheCordovaKaifaZhinan/img/star.png
ApacheCordovaKaifaZhinan/js/__init__.py
ApacheCordovaKaifaZhinan/js/epub.js
ApacheCordovaKaifaZhinan/js/epub.min.js
ApacheCordovaKaifaZhinan/js/epub.min.map
ApacheCordovaKaifaZhinan/js/hooks.min.js
ApacheCordovaKaifaZhinan/js/hooks.min.map
ApacheCordovaKaifaZhinan/js/reader.js
ApacheCordovaKaifaZhinan/js/reader.js.map
ApacheCordovaKaifaZhinan/js/reader.min.js
ApacheCordovaKaifaZhinan/js/reader.min.map
ApacheCordovaKaifaZhinan/js/hooks/__init__.py
ApacheCordovaKaifaZhinan/js/hooks/extensions/__init__.py
ApacheCordovaKaifaZhinan/js/hooks/extensions/highlight.js
ApacheCordovaKaifaZhinan/js/libs/__init__.py
ApacheCordovaKaifaZhinan/js/libs/jquery.min.js
ApacheCordovaKaifaZhinan/js/libs/localforage.min.js
ApacheCordovaKaifaZhinan/js/libs/screenfull.js
apache_cordova_kaifa_zhinan-2024.2.29.0.dist-info/METADATA
apache_cordova_kaifa_zhinan-2024.2.29.0.dist-info/WHEEL
apache_cordova_kaifa_zhinan-2024.2.29.0.dist-info/entry_points.txt
apache_cordova_kaifa_zhinan-2024.2.29.0.dist-info/top_level.txt
apache_cordova_kaifa_zhinan-2024.2.29.0.dist-info/RECORD
